{
  "msg": "操作成功",
  "code": 200,
  "data": [
    {
      "createBy": "admin",
      "createTime": "2025-08-05 08:57:44",
      "updateBy": null,
      "updateTime": null,
      "remark": "显示菜单",
      "params": {
        "@type": "java.util.HashMap"
      },
      "dictCode": 4,
      "dictSort": 1,
      "dictLabel": "显示",
      "dictValue": "0",
      "dictType": "sys_show_hide",
      "cssClass": null,
      "listClass": "primary",
      "isDefault": "Y",
      "status": "0",
      "default": true
    },
    {
      "createBy": "admin",
      "createTime": "2025-08-05 08:57:44",
      "updateBy": null,
      "updateTime": null,
      "remark": "隐藏菜单",
      "params": {
        "@type": "java.util.HashMap"
      },
      "dictCode": 5,
      "dictSort": 2,
      "dictLabel": "隐藏",
      "dictValue": "1",
      "dictType": "sys_show_hide",
      "cssClass": null,
      "listClass": "danger",
      "isDefault": "N",
      "status": "0",
      "default": false
    }
  ]
}